COPYING
README.rst
pyproject.toml
setup.py
contafi/__init__.py
contafi.egg-info/PKG-INFO
contafi.egg-info/SOURCES.txt
contafi.egg-info/dependency_links.txt
contafi.egg-info/requires.txt
contafi.egg-info/top_level.txt
contafi/api_client/__init__.py
contafi/api_client/client/__init__.py
contafi/api_client/client/bhe.py
contafi/api_client/client/bte.py
contafi/api_client/client/contribuyentes.py
contafi/api_client/client/facturacion.py
contafi/api_client/client/ingresos_egresos.py
contafi/api_client/client/remuneraciones.py