Metadata-Version: 2.2
Name: contafi
Version: 2.0.0
Summary: Cliente para realizar la integración con los servicios web de ContaFi desde Python.
Home-page: https://github.com/contafi/contafi-api-client-python
Author: ContaFi
Author-email: dev@contafi.cl
License: LGPL
Keywords: sii chile bhe bte contafi facturacion contribuyentes boleta electronica
Classifier: Development Status :: 5 - Production/Stable
Classifier: Intended Audience :: Developers
Classifier: Topic :: Software Development :: Build Tools
Classifier: License :: OSI Approved :: GNU Lesser General Public License v3 or later (LGPLv3+)
Classifier: Programming Language :: Python :: 3
License-File: COPYING
Requires-Dist: requests
Dynamic: author
Dynamic: author-email
Dynamic: classifier
Dynamic: description
Dynamic: home-page
Dynamic: keywords
Dynamic: license
Dynamic: requires-dist
Dynamic: summary
